[
    {
        "name": "LinkedIn",
        "link": "https://www.linkedin.com/in/oleksii-syrov/",
        "img": "/images/linkedin.png"
    },
    {
        "name": "Instagram",
        "link": "https://www.instagram.com/lexxani42/",
        "img": "/images/instagram.webp"
    },
    {
        "name": "Telegram",
        "link": "http://t.me/lexani42",
        "img": "/images/telegram.webp"
    },
    {
        "name": "GitHub",
        "link": "https://github.com/Lexani42",
        "img": "/images/github.png"
    },
    {
        "name": "Email",
        "link": "mailto:lexxani42@gmail.com",
        "img": "/images/gmail.png"
    },
    {
        "name": "Phone",
        "link": "tel:+380680451051",
        "img": "/images/phone.png"
    }
]